[{"link":"/players/h/hillsi01.html","season":"1969-70","club":"TOT"},{"link":"/players/h/hillsi01.html","season":"1969-70","club":"LAS"},{"link":"/players/h/hillsi01.html","season":"1969-70","club":"MMF"},{"link":"/players/h/hillsi01.html","season":"","club":"Did Not Play"},{"link":"/players/h/hillsi01.html","season":"1971-72","club":"DLC"},{"link":"/players/h/hillsi01.html","season":"1972-73","club":"SDA"},{"link":"/players/h/hillsi01.html","season":"1973-74","club":"SAA"},{"link":"/players/h/hillso01.html","season":"2013-14","club":"IND"},{"link":"/players/h/hillso01.html","season":"2014-15","club":"IND"},{"link":"/players/h/hillso01.html","season":"2015-16","club":"IND"},{"link":"/players/h/hillso01.html","season":"2016-17","club":"NOP"},{"link":"/players/h/hillso01.html","season":"2017-18","club":"NOP"},{"link":"/players/h/hillso01.html","season":"2018-19","club":"NOP"},{"link":"/players/h/hillso01.html","season":"2019-20","club":"TOT"},{"link":"/players/h/hillso01.html","season":"2019-20","club":"MEM"},{"link":"/players/h/hillso01.html","season":"2019-20","club":"MIA"},{"link":"/players/h/hillst01.html","season":"2008-09","club":"OKC"},{"link":"/players/h/hillty01.html","season":"1990-91","club":"GSW"},{"link":"/players/h/hillty01.html","season":"1991-92","club":"GSW"},{"link":"/players/h/hillty01.html","season":"1992-93","club":"GSW"},{"link":"/players/h/hillty01.html","season":"1993-94","club":"CLE"},{"link":"/players/h/hillty01.html","season":"1994-95","club":"CLE"},{"link":"/players/h/hillty01.html","season":"1995-96","club":"CLE"},{"link":"/players/h/hillty01.html","season":"1996-97","club":"CLE"},{"link":"/players/h/hillty01.html","season":"1997-98","club":"MIL"},{"link":"/players/h/hillty01.html","season":"1998-99","club":"TOT"},{"link":"/players/h/hillty01.html","season":"1998-99","club":"MIL"},{"link":"/players/h/hillty01.html","season":"1998-99","club":"PHI"},{"link":"/players/h/hillty01.html","season":"1999-00","club":"PHI"},{"link":"/players/h/hillty01.html","season":"2000-01","club":"PHI"},{"link":"/players/h/hillty01.html","season":"2001-02","club":"CLE"},{"link":"/players/h/hillty01.html","season":"2002-03","club":"TOT"},{"link":"/players/h/hillty01.html","season":"2002-03","club":"CLE"},{"link":"/players/h/hillty01.html","season":"2002-03","club":"PHI"},{"link":"/players/h/hillty01.html","season":"2003-04","club":"MIA"},{"link":"/players/h/hillhar01.html","season":"1946-47","club":"PHW"},{"link":"/players/h/hillhar01.html","season":"1947-48","club":"PHW"},{"link":"/players/h/hillida01.html","season":"2015-16","club":"DET"},{"link":"/players/h/hillida01.html","season":"2016-17","club":"DET"},{"link":"/players/h/hillida01.html","season":"2017-18","club":"SAS"},{"link":"/players/h/hillmda01.html","season":"1971-72","club":"INA"},{"link":"/players/h/hillmda01.html","season":"1972-73","club":"INA"},{"link":"/players/h/hillmda01.html","season":"1973-74","club":"INA"},{"link":"/players/h/hillmda01.html","season":"1974-75","club":"INA"},{"link":"/players/h/hillmda01.html","season":"1975-76","club":"INA"},{"link":"/players/h/hillmda01.html","season":"1976-77","club":"IND"},{"link":"/players/h/hillmda01.html","season":"1977-78","club":"TOT"},{"link":"/players/h/hillmda01.html","season":"1977-78","club":"NJN"},{"link":"/players/h/hillmda01.html","season":"1977-78","club":"DEN"},{"link":"/players/h/hillmda01.html","season":"1978-79","club":"KCK"},{"link":"/players/h/hillmda01.html","season":"1979-80","club":"GSW"},{"link":"/players/h/hiltofr01.html","season":"1971-72","club":"BUF"},{"link":"/players/h/hiltofr01.html","season":"1972-73","club":"BUF"},{"link":"/players/h/hinriki01.html","season":"2003-04","club":"CHI"},{"link":"/players/h/hinriki01.html","season":"2004-05","club":"CHI"},{"link":"/players/h/hinriki01.html","season":"2005-06","club":"CHI"},{"link":"/players/h/hinriki01.html","season":"2006-07","club":"CHI"},{"link":"/players/h/hinriki01.html","season":"2007-08","club":"CHI"},{"link":"/players/h/hinriki01.html","season":"2008-09","club":"CHI"},{"link":"/players/h/hinriki01.html","season":"2009-10","club":"CHI"},{"link":"/players/h/hinriki01.html","season":"2010-11","club":"TOT"},{"link":"/players/h/hinriki01.html","season":"2010-11","club":"WAS"},{"link":"/players/h/hinriki01.html","season":"2010-11","club":"ATL"},{"link":"/players/h/hinriki01.html","season":"2011-12","club":"ATL"},{"link":"/players/h/hinriki01.html","season":"2012-13","club":"CHI"},{"link":"/players/h/hinriki01.html","season":"2013-14","club":"CHI"},{"link":"/players/h/hinriki01.html","season":"2014-15","club":"CHI"},{"link":"/players/h/hinriki01.html","season":"2015-16","club":"TOT"},{"link":"/players/h/hinriki01.html","season":"2015-16","club":"CHI"},{"link":"/players/h/hinriki01.html","season":"2015-16","club":"ATL"},{"link":"/players/h/hinsoro01.html","season":"1983-84","club":"CLE"},{"link":"/players/h/hinsoro01.html","season":"1984-85","club":"CLE"},{"link":"/players/h/hinsoro01.html","season":"1985-86","club":"CLE"},{"link":"/players/h/hinsoro01.html","season":"1986-87","club":"PHI"},{"link":"/players/h/hinsoro01.html","season":"1987-88","club":"TOT"},{"link":"/players/h/hinsoro01.html","season":"1987-88","club":"PHI"},{"link":"/players/h/hinsoro01.html","season":"1987-88","club":"NJN"},{"link":"/players/h/hinsoro01.html","season":"1988-89","club":"NJN"},{"link":"/players/h/hinsoro01.html","season":"1989-90","club":"NJN"},{"link":"/players/h/hinsoro01.html","season":"1990-91","club":"NJN"},{"link":"/players/h/hirscme01.html","season":"1946-47","club":"BOS"},{"link":"/players/h/hitchle01.html","season":"1951-52","club":"MNL"},{"link":"/players/h/hitchle01.html","season":"1952-53","club":"MNL"},{"link":"/players/h/hitchle01.html","season":"1953-54","club":"MLH"},{"link":"/players/h/hitchle01.html","season":"1954-55","club":"TOT"},{"link":"/players/h/hitchle01.html","season":"1954-55","club":"MLH"},{"link":"/players/h/hitchle01.html","season":"1954-55","club":"MNL"},{"link":"/players/h/hitchle01.html","season":"1955-56","club":"MNL"},{"link":"/players/h/hitchle01.html","season":"1956-57","club":"TOT"},{"link":"/players/h/hitchle01.html","season":"1956-57","club":"ROC"},{"link":"/players/h/hitchle01.html","season":"1956-57","club":"PHW"},{"link":"/players/h/hitero01.html","season":"2006-07","club":"MIA"},{"link":"/players/h/hoardja01.html","season":"2019-20","club":"POR"},{"link":"/players/h/hobsoda01.html","season":"2011-12","club":"MIL"},{"link":"/players/h/hodgedo01.html","season":"1991-92","club":"DAL"},{"link":"/players/h/hodgedo01.html","season":"1992-93","club":"DAL"},{"link":"/players/h/hodgedo01.html","season":"1993-94","club":"DAL"},{"link":"/players/h/hodgedo01.html","season":"1994-95","club":"DAL"},{"link":"/players/h/hodgedo01.html","season":"1995-96","club":"TOT"},{"link":"/players/h/hodgedo01.html","season":"1995-96","club":"DAL"},{"link":"/players/h/hodgedo01.html","season":"1995-96","club":"CHH"},{"link":"/players/h/hodgeju01.html","season":"2005-06","club":"DEN"},{"link":"/players/h/hodgeju01.html","season":"2006-07","club":"TOT"},{"link":"/players/h/hodgeju01.html","season":"2006-07","club":"DEN"},{"link":"/players/h/hodgeju01.html","season":"2006-07","club":"MIL"},{"link":"/players/h/hodgecr01.html","season":"1982-83","club":"SDC"},{"link":"/players/h/hodgecr01.html","season":"1983-84","club":"SDC"},{"link":"/players/h/hodgecr01.html","season":"1984-85","club":"MIL"},{"link":"/players/h/hodgecr01.html","season":"1985-86","club":"MIL"},{"link":"/players/h/hodgecr01.html","season":"1986-87","club":"MIL"},{"link":"/players/h/hodgecr01.html","season":"1987-88","club":"TOT"},{"link":"/players/h/hodgecr01.html","season":"1987-88","club":"MIL"},{"link":"/players/h/hodgecr01.html","season":"1987-88","club":"PHO"},{"link":"/players/h/hodgecr01.html","season":"1988-89","club":"TOT"},{"link":"/players/h/hodgecr01.html","season":"1988-89","club":"PHO"},{"link":"/players/h/hodgecr01.html","season":"1988-89","club":"CHI"},{"link":"/players/h/hodgecr01.html","season":"1989-90","club":"CHI"},{"link":"/players/h/hodgecr01.html","season":"1990-91","club":"CHI"},{"link":"/players/h/hodgecr01.html","season":"1991-92","club":"CHI"},{"link":"/players/h/hoefech01.html","season":"1946-47","club":"TOT"},{"link":"/players/h/hoefech01.html","season":"1946-47","club":"TRH"},{"link":"/players/h/hoefech01.html","season":"1946-47","club":"BOS"},{"link":"/players/h/hoefech01.html","season":"1947-48","club":"BOS"},{"link":"/players/h/hoffmpa01.html","season":"1947-48","club":"BLB"},{"link":"/players/h/hoffmpa01.html","season":"","club":"Did Not Play (illness—heart condition)"},{"link":"/players/h/hoffmpa01.html","season":"1949-50","club":"BLB"},{"link":"/players/h/hoffmpa01.html","season":"1950-51","club":"BLB"},{"link":"/players/h/hoffmpa01.html","season":"","club":"Did Not Play (illness—heart condition)"},{"link":"/players/h/hoffmpa01.html","season":"1952-53","club":"BLB"},{"link":"/players/h/hoffmpa01.html","season":"1953-54","club":"BLB"},{"link":"/players/h/hoffmpa01.html","season":"1954-55","club":"TOT"},{"link":"/players/h/hoffmpa01.html","season":"1954-55","club":"BLB"},{"link":"/players/h/hoffmpa01.html","season":"1954-55","club":"NYK"},{"link":"/players/h/hoffmpa01.html","season":"1954-55","club":"PHW"},{"link":"/players/h/hogsebo01.html","season":"1966-67","club":"DET"},{"link":"/players/h/hogsebo01.html","season":"1967-68","club":"PTP"},{"link":"/players/h/hoguedu01.html","season":"1962-63","club":"NYK"},{"link":"/players/h/hoguedu01.html","season":"1963-64","club":"TOT"},{"link":"/players/h/hoguedu01.html","season":"1963-64","club":"NYK"},{"link":"/players/h/hoguedu01.html","season":"1963-64","club":"BAL"},{"link":"/players/h/hoibefr01.html","season":"1995-96","club":"IND"},{"link":"/players/h/hoibefr01.html","season":"1996-97","club":"IND"},{"link":"/players/h/hoibefr01.html","season":"1997-98","club":"IND"},{"link":"/players/h/hoibefr01.html","season":"1998-99","club":"IND"},{"link":"/players/h/hoibefr01.html","season":"1999-00","club":"CHI"},{"link":"/players/h/hoibefr01.html","season":"2000-01","club":"CHI"},{"link":"/players/h/hoibefr01.html","season":"2001-02","club":"CHI"},{"link":"/players/h/hoibefr01.html","season":"2002-03","club":"CHI"},{"link":"/players/h/hoibefr01.html","season":"2003-04","club":"MIN"},{"link":"/players/h/hoibefr01.html","season":"2004-05","club":"MIN"},{"link":"/players/h/holcodo01.html","season":"1948-49","club":"BLB"}]